README.md
aiocronjob/__init__.py
aiocronjob/api.py
aiocronjob/dependencies.py
aiocronjob/exceptions.py
aiocronjob/logger.py
aiocronjob/main.py
aiocronjob/manager.py
aiocronjob/models.py
aiocronjob/util.py
aiocronjob-0.7.0.dist-info/WHEEL
aiocronjob-0.7.0.dist-info/METADATA
aiocronjob-0.7.0.dist-info/licenses/LICENSE
aiocronjob-0.7.0.dist-info/RECORD
