Metadata-Version: 2.1
Name: aiocronjob
Version: 0.7.0
Summary: Schedule async tasks and manage them using a REST API or WEB UI
License: MIT
Keywords: async tasks,crontab,rest api
Author-email: devtud <devtud@gmail.com>
Maintainer-email: devtud <devtud@gmail.com>
Requires-Python: >=3.8
Classifier: Development Status :: 3 - Alpha
Classifier: Framework :: AsyncIO
Classifier: Intended Audience :: Developers
Classifier: License :: OSI Approved :: MIT License
Classifier: Programming Language :: Python :: 3 :: Only
Classifier: Programming Language :: Python :: 3.10
Classifier: Programming Language :: Python :: 3.8
Classifier: Programming Language :: Python :: 3.9
Classifier: Topic :: Internet :: WWW/HTTP :: HTTP Servers
Classifier: Topic :: Software Development :: Libraries :: Application Frameworks
Requires-Dist: aiofiles>=0.5.0
Requires-Dist: async-asgi-testclient>=1.4.11
Requires-Dist: crontab>=0.22.8
Requires-Dist: pytz>=2020.1
Requires-Dist: starlite>=1.40.0
Requires-Dist: uvicorn>=0.11.5
Project-URL: homepage, https://github.com/devtud/aiocronjob
Project-URL: repository, https://github.com/devtud/aiocronjob
